drakkar_odoo_init/__init__.py
drakkar_odoo_init/cli.py
drakkar_odoo_init/setup.py
drakkar_odoo_init-0.1.0.dist-info/METADATA
drakkar_odoo_init-0.1.0.dist-info/WHEEL
drakkar_odoo_init-0.1.0.dist-info/entry_points.txt
drakkar_odoo_init-0.1.0.dist-info/RECORD
