Metadata-Version: 2.4
Name: drakkar-odoo-init
Version: 0.1.0
Summary: Outil d'initialisation de projets Odoo pour Drakkar
Author: Drakkar Team
Classifier: Operating System :: OS Independent
Classifier: Programming Language :: Python :: 3
Requires-Python: >=3.8
